motion2telegram/__init__.py
motion2telegram/cli.py
motion2telegram/configure.py
motion2telegram/send.py
motion2telegram/template.mobile_phone_scan.service
motion2telegram/template.motion.conf
motion2telegram/template.motion.env
motion2telegram/template.motion.service
motion2telegram-1.2.1.dist-info/LICENSE
motion2telegram-1.2.1.dist-info/METADATA
motion2telegram-1.2.1.dist-info/WHEEL
motion2telegram-1.2.1.dist-info/entry_points.txt
motion2telegram-1.2.1.dist-info/top_level.txt
motion2telegram-1.2.1.dist-info/RECORD
