Metadata-Version: 2.1
Name: motion2telegram
Version: 1.2.1
Summary: Notify a Telegram user when the motion service detects motion
Author-email: p4irin <p4irin.github.io@gmail.com>
Project-URL: Homepage, https://github.com/p4irin/motion2telegram
Project-URL: Bug Tracker, https://github.com/p4irin/motion2telegram/issues
Keywords: motion,python,telegram,motion-detection,webcam,raspberry-pi
Classifier: Environment :: Console
Classifier: Topic :: Home Automation
Classifier: Intended Audience :: System Administrators
Classifier: Programming Language :: Python :: 3
Classifier: Programming Language :: Python :: 3.11
Classifier: Operating System :: POSIX :: Linux
Classifier: License :: OSI Approved :: MIT License
Requires-Python: >=3.8.10
License-File: LICENSE
Requires-Dist: telegram-notifier-bot >=1.0.0
Provides-Extra: dev
Requires-Dist: bumpver >=2023.1126 ; extra == 'dev'
Requires-Dist: motion2telegram[lint] ; extra == 'dev'
Requires-Dist: motion2telegram[package] ; extra == 'dev'
Provides-Extra: lint
Requires-Dist: mypy >=1.9.0 ; extra == 'lint'
Requires-Dist: ruff >=0.3.4 ; extra == 'lint'
Requires-Dist: types-requests >=2.32.0.20240602 ; extra == 'lint'
Provides-Extra: package
Requires-Dist: build ==0.10.0 ; extra == 'package'
Requires-Dist: twine >=4.0.2 ; extra == 'package'
